pstarbound-1.3.0.dist-info/licenses/LICENSE
starbound/__init__.py
starbound/btreedb5.py
starbound/cli.py
starbound/cliexport.py
starbound/cliregion.py
starbound/clirepair.py
starbound/materials.py
starbound/modgen.py
starbound/render.py
starbound/sbasset6.py
starbound/sbon.py
starbound/shipworld.py
starbound/workshop.py
pstarbound-1.3.0.dist-info/METADATA
pstarbound-1.3.0.dist-info/WHEEL
pstarbound-1.3.0.dist-info/entry_points.txt
pstarbound-1.3.0.dist-info/top_level.txt
pstarbound-1.3.0.dist-info/RECORD
