Metadata-Version: 2.4
Name: pstarbound
Version: 1.3.0
Summary: Python utilities for Starbound files, plus shipworld rendering and mod generation
Requires-Python: >=3.9
License-File: LICENSE
Provides-Extra: ship
Requires-Dist: pillow>=10; extra == "ship"
Provides-Extra: workshop
Requires-Dist: vdf>=3.4; extra == "workshop"
Dynamic: license-file
